<?xml version="1.0" encoding="UTF-8"?>
<Index xmlns="http://www.tso.co.uk/assets/namespace/gazetteindex" editionCode="L" page="196" pageID="https://www.thegazette.co.uk/id/London/index/year/1916/volume/4/page/196" pagePDF="https://www.thegazette.co.uk/London/index/year/1916/volume/4/page/196" pageRDF="https://www.thegazette.co.uk/London/index/year/1916/volume/4/page/196?view=linked-data" type="index" volume="4" year="1916">
  <ItemGroup>
    <MainItem>
      <Key>Grice-Hutchinson</Key>
      <Title>(temp.) Lt. (temp, Capt.)</Title>
      <Forenames>C. G.</Forenames>
      <Text>(temp. Capt. to complete estab.)</Text>
      <PageNumber>9846</PageNumber>
    </MainItem>
  </ItemGroup>
  <ItemGroup>
    <MainItem>
      <Key>Grierson</Key>
      <Title>Cadet</Title>
      <Forenames>C. P.</Forenames>
      <Text>(temp. 2nd Lt. on prbb.)</Text>
      <PageNumber>10861</PageNumber>
    </MainItem>
    <SubItem>
      <Text>H A., M.B. (temp. Lt.)</Text>
      <PageNumber>12483</PageNumber>
    </SubItem>
    <SubItem>
      <Text>Lt. (actg. Capt.) W. A. (temp. Capt., Smb. Not.)</Text>
      <PageNumber>11580</PageNumber>
    </SubItem>
    <SubItem>
      <Text>
        <PageNumber>11580</PageNumber>
      </Text>
      <PageNumber>10504</PageNumber>
    </SubItem>
  </ItemGroup>
  <ItemGroup>
    <MainItem>
      <Key>Grieve</Key>
      <Title>(temp.) 2nd Lt.</Title>
      <Forenames>W. G.</Forenames>
      <Text>(temp. Lt.)</Text>
      <PageNumber>11113</PageNumber>
    </MainItem>
    <SubItem>
      <Text>(temp.) 2nd Lt. W. W. (trd.)</Text>
      <PageNumber>9823</PageNumber>
      <PageNumber>10232</PageNumber>
    </SubItem>
  </ItemGroup>
  <ItemGroup>
    <MainItem>
      <Key>Grieveson</Key>
      <Title>(temp.) Lt.</Title>
      <Forenames>E. R.</Forenames>
      <Text>, M.B. (temp. Capt.)</Text>
      <PageNumber>12482</PageNumber>
    </MainItem>
  </ItemGroup>
  <ItemGroup>
    <MainItem>
      <Key>Griffin</Key>
      <Title>(temp.) Maj.</Title>
      <Forenames>A. E. S.</Forenames>
      <Text>(rel. rank of temp. Lt.-Col.)</Text>
      <PageNumber>10263</PageNumber>
    </MainItem>
    <SubItem>
      <Text>
        <PageNumber>10428</PageNumber>
        <PageNumber>12329</PageNumber>
      </Text>
      <PageNumber>12199</PageNumber>
    </SubItem>
    <KeyDitto>——</KeyDitto>
    <SubItem>
      <Text>studies)</Text>
      <PageNumber>9747</PageNumber>
    </SubItem>
  </ItemGroup>
  <ItemGroup>
    <MainItem>
      <Key>
        <KeyDitto>—</KeyDitto>
      </Key>
      <Title>(temp.) Lt.</Title>
      <Forenames>F. N.</Forenames>
      <Text>(trd.)</Text>
      <PageNumber>9943</PageNumber>
    </MainItem>
    <SubItem>
      <Text>
        <PageNumber>10034</PageNumber>
        <PageNumber>12483</PageNumber>
        <PageNumber>35</PageNumber>
        <PageNumber>10288</PageNumber>
        <PageNumber>11133</PageNumber>
      </Text>
      <PageNumber>11680</PageNumber>
    </SubItem>
    <SubItem>
      <Text>
        <PageNumber>10089</PageNumber>
      </Text>
      <PageNumber>9938</PageNumber>
    </SubItem>
  </ItemGroup>
  <ItemGroup>
    <MainItem>
      <Key>Griffith</Key>
      <Forenames>Cadat A. C. F.</Forenames>
      <Text>(2nd Lt.)</Text>
      <PageNumber>10406</PageNumber>
    </MainItem>
    <SubItem>
      <Text>(temp.) 2nd Lt. A. K. (rel. commn. on acc. of illhealth)</Text>
      <PageNumber>10862</PageNumber>
    </SubItem>
    <SubItem>
      <Text>B. W. (temp. 2nd L. on prob.)</Text>
      <PageNumber>10639</PageNumber>
    </SubItem>
    <SubItem>
      <Text>(temp.) 2nd Lt . (on prob.) C. F. (confd.)</Text>
      <PageNumber>9617</PageNumber>
    </SubItem>
    <SubItem>
      <Text>
        <Honour>D.S.O.</Honour>
      </Text>
      <PageNumber>11124</PageNumber>
    </SubItem>
    <SubItem>
      <Text>2nd Lt. (on prob.) E. N. (confd.)</Text>
      <PageNumber>10829</PageNumber>
    </SubItem>
    <SubItem>
      <Text>
        <PageNumber>11680</PageNumber>
      </Text>
      <PageNumber>12428</PageNumber>
    </SubItem>
    <SubItem>
      <Text>Cadet.G. H. (temp. 2nd Lt. on prob.)</Text>
      <PageNumber>11603</PageNumber>
    </SubItem>
    <SubItem>
      <Text>Cadet H. F. (temp. 2nd Lt. oh prob.)</Text>
      <PageNumber>9958</PageNumber>
    </SubItem>
  </ItemGroup>
  <ItemGroup>
    <MainItem>
      <Key>
        <KeyDitto>——</KeyDitto>
      </Key>
      <Title>(temp.) 2nd Lt.</Title>
      <Forenames>H. L.</Forenames>
      <Text>(temp. Lt.)</Text>
      <PageNumber>11113</PageNumber>
    </MainItem>
    <SubItem>
      <Text>(temp.) Capt. I. (trd.)</Text>
      <PageNumber>11128</PageNumber>
    </SubItem>
    <SubItem>
      <Text>2nd Lt. (on prob.) J. E. (confd.)</Text>
      <PageNumber>11609</PageNumber>
    </SubItem>
    <SubItem>
      <Text>
        <PageNumber>10091</PageNumber>
      </Text>
      <PageNumber>9843</PageNumber>
    </SubItem>
    <SubItem>
      <Text>(temp.) 2nd Lt. R. H. L. (trd.)</Text>
      <PageNumber>11415</PageNumber>
    </SubItem>
  </ItemGroup>
  <ItemGroup>
    <MainItem>
      <Key>
        <KeyDitto>—</KeyDitto>
      </Key>
      <Title>2nd Lt.</Title>
      <Forenames>T. C.</Forenames>
      <Text>(Lt.)</Text>
      <PageNumber>9937</PageNumber>
    </MainItem>
    <SubItem>
      <Text>Cadet W. H. (temp. 2nd Lt. on prob.)</Text>
      <PageNumber>12234</PageNumber>
    </SubItem>
  </ItemGroup>
  <ItemGroup>
    <MainItem>
      <Key>
        <KeyDitto>—</KeyDitto>
      </Key>
      <Title>(temp.) 2nd Lt.</Title>
      <Forenames>W. L</Forenames>
      <Text>(trd.)</Text>
      <PageNumber>10504</PageNumber>
    </MainItem>
  </ItemGroup>
  <ItemGroup>
    <MainItem>
      <Key>Griffith-Boscawen</Key>
      <Title>Lt.-Col. Sir</Title>
      <Forenames>A. S. T.</Forenames>
      <Text>(temp. Lt.-Cbl.) (Sub. Not.)</Text>
      <PageNumber>12738</PageNumber>
    </MainItem>
    <SubItem>
      <Text>(temp.) Lt. J. (rel. actg. rank of Capt.)</Text>
      <PageNumber>11684</PageNumber>
    </SubItem>
    <SubItem>
      <Text>(temp.) Capt. M. P. (trd.)</Text>
      <PageNumber>10292</PageNumber>
    </SubItem>
  </ItemGroup>
  <ItemGroup>
    <MainItem>
      <Key>Griffiths</Key>
      <Title>Cadet</Title>
      <Forenames>A. G.</Forenames>
      <Text>(temp. 2nd Lt. on prob.)</Text>
      <PageNumber>11377</PageNumber>
    </MainItem>
    <SubItem>
      <Text>Cadet A. I. (temp. 2nd Lt. on prob.)</Text>
      <PageNumber>10425</PageNumber>
    </SubItem>
    <SubItem>
      <Text>(temp.) 2nd Lt. A. W. (temp. Capt.)</Text>
      <PageNumber>12311</PageNumber>
    </SubItem>
    <SubItem>
      <Text>Cadet E. C. (temp. 2nd Lt. on prob.)</Text>
      <PageNumber>11257</PageNumber>
    </SubItem>
    <SubItem>
      <Text>Cadet F. H. (2nd Lt. on prob.)</Text>
      <PageNumber>11975</PageNumber>
    </SubItem>
    <SubItem>
      <Text>
        <PageNumber>10507</PageNumber>
      </Text>
      <PageNumber>9648</PageNumber>
    </SubItem>
    <SubItem>
      <Text>Driver Hj. B. (temp. 2rid Lt. on prob.)</Text>
      <PageNumber>11566</PageNumber>
    </SubItem>
    <SubItem>
      <Text>
        <PageNumber>10389</PageNumber>
        <PageNumber>10835</PageNumber>
      </Text>
      <PageNumber>12479</PageNumber>
    </SubItem>
    <SubItem>
      <Text>Lt. M. O. I. (Capt.)</Text>
      <PageNumber>10401</PageNumber>
    </SubItem>
    <SubItem>
      <Text>Rev. R, (rsl. commn.)</Text>
      <PageNumber>12199</PageNumber>
    </SubItem>
    <SubItem>
      <Text>
        <PageNumber>10972</PageNumber>
        <PageNumber>10387</PageNumber>
        <PageNumber>11688</PageNumber>
      </Text>
      <PageNumber>11112</PageNumber>
    </SubItem>
    <SubItem>
      <Text>(temp.) 2nd Lt. W. C. (trd.)</Text>
      <PageNumber>10753</PageNumber>
    </SubItem>
    <SubItem>
      <Text>(temp.) 2nd Lt. W. J. (trd.) * * '</Text>
      <PageNumber>10504</PageNumber>
      <PageNumber>10828</PageNumber>
    </SubItem>
  </ItemGroup>
  <ItemGroup>
    <MainItem>
      <Key>Grigg</Key>
      <Title>Cadet</Title>
      <Forenames>A. N.</Forenames>
      <Text>(2nd Lt. on prob.)</Text>
      <PageNumber>10389</PageNumber>
    </MainItem>
    <SubItem>
      <Text>
        <PageNumber>258</PageNumber>
      </Text>
      <PageNumber>12460</PageNumber>
    </SubItem>
  </ItemGroup>
  <ItemGroup>
    <MainItem>
      <Key>Griggs</Key>
      <Forenames>A. G.</Forenames>
      <Text>(2nd Lt. on prob.)</Text>
      <PageNumber>11681</PageNumber>
    </MainItem>
    <SubItem>
      <Text>-Cadet ' W. J. (2nd Lt. on prob.)</Text>
      <PageNumber>11738</PageNumber>
    </SubItem>
  </ItemGroup>
  <ItemGroup>
    <MainItem>
      <Key>Grime</Key>
      <Title>(temp.) 2nd Lt.</Title>
      <Forenames>A. J.</Forenames>
      <Text>(trd.)</Text>
      <PageNumber>10388</PageNumber>
      <PageNumber>11163</PageNumber>
    </MainItem>
  </ItemGroup>
  <ItemGroup>
    <MainItem>
      <Key>Grimes</Key>
      <Title>(temp.) Lt.</Title>
      <Forenames>A. V.</Forenames>
      <Text>(trd.)</Text>
      <PageNumber>11580</PageNumber>
    </MainItem>
    <SubItem>
      <Text>(temp.) Capt. M. J. D. (temp. Maj.)</Text>
      <PageNumber>9871</PageNumber>
    </SubItem>
  </ItemGroup>
  <ItemGroup>
    <MainItem>
      <Key>Grimke-Dray</Key>
      <Text>ton, Lt. A. D. (.Capt.)</Text>
      <PageNumber>10942</PageNumber>
    </MainItem>
  </ItemGroup>
  <ItemGroup>
    <MainItem>
      <Key>Grimley</Key>
      <Title>2nd Lt.</Title>
      <Forenames>C. W. G.</Forenames>
      <Text>(temp. Lt.) ... '</Text>
      <PageNumber>12462</PageNumber>
    </MainItem>
    <SubItem>
      <Text>
        <PageNumber>11393</PageNumber>
      </Text>
      <PageNumber>10406</PageNumber>
    </SubItem>
  </ItemGroup>
  <ItemGroup>
    <MainItem>
      <Key>Grimsdale</Key>
      <Title>(temp.) 2nd Lt.</Title>
      <Forenames>A. G.</Forenames>
      <Text>(trd.)</Text>
      <PageNumber>10385</PageNumber>
    </MainItem>
    <SubItem>
      <Text>Lt. G. E. (actg. Capt.)</Text>
      <PageNumber>12662</PageNumber>
    </SubItem>
  </ItemGroup>
  <ItemGroup>
    <MainItem>
      <Key>Grimshaw</Key>
      <Title>(temp.) Maj.</Title>
      <Forenames>C.</Forenames>
      <Text>(trd.)</Text>
      <PageNumber>10401</PageNumber>
    </MainItem>
    <SubItem>
      <Text>(temp.) Capt. C. H. (trd.)</Text>
      <PageNumber>10957</PageNumber>
    </SubItem>
    <SubItem>
      <Text>2nd Lt. W. E. (temp. Lt.)</Text>
      <PageNumber>11114</PageNumber>
    </SubItem>
  </ItemGroup>
  <ItemGroup>
    <MainItem>
      <Key>Grimson</Key>
      <Title>(temp.) Capt.</Title>
      <Forenames>T.</Forenames>
      <Text>, M.B. (rel. commn.)</Text>
      <PageNumber>12481</PageNumber>
    </MainItem>
  </ItemGroup>
  <ItemGroup>
    <MainItem>
      <Key>Grimston</Key>
      <Title>Cadet</Title>
      <Forenames>R. V</Forenames>
      <Text>: (2nd Lt. on prob.)</Text>
      <PageNumber>9652</PageNumber>
    </MainItem>
  </ItemGroup>
  <ItemGroup>
    <MainItem>
      <Key>Grimwade</Key>
      <Title>(temp.) Capt.</Title>
      <Forenames>H. C.</Forenames>
      <Text>(Adjt.)</Text>
      <PageNumber>12739</PageNumber>
    </MainItem>
  </ItemGroup>
  <ItemGroup>
    <MainItem>
      <Key>Grimwood</Key>
      <Title>(temp.) 2nd Lt.</Title>
      <Forenames>A.</Forenames>
      <Text>(actg. Lt.)</Text>
      <PageNumber>11583</PageNumber>
    </MainItem>
  </ItemGroup>
  <ItemGroup>
    <MainItem>
      <Key>Grindell</Key>
      <Title>Serjt.</Title>
      <Forenames>H.</Forenames>
      <Text>(temp. 2nd Lt. on prob.)</Text>
      <PageNumber>10839</PageNumber>
    </MainItem>
  </ItemGroup>
  <ItemGroup>
    <MainItem>
      <Key>Grindlay</Key>
      <Title>Cadet</Title>
      <Forenames>A. B.</Forenames>
      <Text>(temp. 2nd Lt. on prob.)</Text>
      <PageNumber>11580</PageNumber>
    </MainItem>
  </ItemGroup>
  <ItemGroup>
    <MainItem>
      <Key>Grindley</Key>
      <Title>(temp.) 2nd Lt.</Title>
      <Forenames>R. L.</Forenames>
      <Text>(trd.) ..:</Text>
      <PageNumber>10428</PageNumber>
    </MainItem>
  </ItemGroup>
  <ItemGroup>
    <MainItem>
      <Key>
        <KeyDitto>—</KeyDitto>
      </Key>
      <Title>(temp.) 2nd Lt.</Title>
      <Forenames>W. G.</Forenames>
      <Text>(trd</Text>
      <PageNumber>10428</PageNumber>
    </MainItem>
  </ItemGroup>
  <ItemGroup>
    <MainItem>
      <Key>Grinham</Key>
      <Title>Cadet</Title>
      <Forenames>F. B.</Forenames>
      <Text>(temp. 2nd Lt. on prob.)</Text>
      <PageNumber>10861</PageNumber>
    </MainItem>
  </ItemGroup>
  <ItemGroup>
    <MainItem>
      <Key>Grinsted</Key>
      <Title>(temp.) 2nd Lt.</Title>
      <Forenames>M.</Forenames>
      <Text>(trd.)</Text>
      <PageNumber>10429</PageNumber>
    </MainItem>
  </ItemGroup>
  <ItemGroup>
    <MainItem>
      <Key>Gripper</Key>
      <Title>Jtemp.</Title>
      <Text>) 2nd ' Lt. A. J. Gen. List, temp. Capt.)</Text>
      <PageNumber>10600</PageNumber>
    </MainItem>
    <SubItem>
      <Text>
        <PageNumber>11926</PageNumber>
      </Text>
      <PageNumber>10628</PageNumber>
    </SubItem>
  </ItemGroup>
  <ItemGroup>
    <MainItem>
      <Key>Griss</Key>
      <Forenames>Riding</Forenames>
      <Text>Master and Hon. . . Maj, J. E. (Hon. Lt.-Col.)</Text>
      <PageNumber>11923</PageNumber>
    </MainItem>
  </ItemGroup>
  <ItemGroup>
    <MainItem>
      <Key>Grissell</Key>
      <Title>Maj.</Title>
      <Forenames>B. S.</Forenames>
      <Text>(temp. Lt.Col.)</Text>
      <PageNumber>9536</PageNumber>
    </MainItem>
    <SubItem>
      <Text>2nd Lt. F. (Lt.)</Text>
      <PageNumber>10070</PageNumber>
    </SubItem>
  </ItemGroup>
  <ItemGroup>
    <MainItem>
      <Key>Grist</Key>
      <Title>(temp.) Maj.</Title>
      <Forenames>H. G.</Forenames>
      <Text>(temp. Lt.-Col.)</Text>
      <PageNumber>10425</PageNumber>
    </MainItem>
    <SubItem>
      <Text>Rel. actg. rank of Lt.-Col.</Text>
      <PageNumber>11948</PageNumber>
    </SubItem>
  </ItemGroup>
  <ItemGroup>
    <MainItem>
      <Key>Groager</Key>
      <Title>(temp.) 2nd Lt.</Title>
      <Forenames>N. E. S.</Forenames>
      <Text>(trd.) ... :</Text>
      <PageNumber>10385</PageNumber>
    </MainItem>
  </ItemGroup>
  <ItemGroup>
    <MainItem>
      <Key>Groner</Key>
      <Title>(temp.) 2nd Lt.</Title>
      <Forenames>R. E. E.</Forenames>
      <PageNumber>10505</PageNumber>
    </MainItem>
    <SubItem>
      <Text>(trd.)</Text>
      <PageNumber>10262</PageNumber>
    </SubItem>
  </ItemGroup>
  <ItemGroup>
    <MainItem>
      <Key>Gronow</Key>
      <Title>Lee.</Title>
      <Text>-Serjt. T. (2nd Lt.) Groom, (temp.) 2nd Lt. A. C. H</Text>
      <PageNumber>10092</PageNumber>
    </MainItem>
    <SubItem>
      <Text>(trd.).</Text>
      <PageNumber>9750</PageNumber>
    </SubItem>
  </ItemGroup>
  <ItemGroup>
    <MainItem>
      <Key>
        <KeyDitto>—</KeyDitto>
      </Key>
      <Title>Pte.</Title>
      <Forenames>C. R. N.</Forenames>
      <Text>(temp. 2nd Lt</Text>
      <PageNumber>12488</PageNumber>
    </MainItem>
  </ItemGroup>
  <ItemGroup>
    <MainItem>
      <Key>
        <KeyDitto>—</KeyDitto>
      </Key>
      <Title>(temp.) 2nd Lt.</Title>
      <Forenames>E. A. H.</Forenames>
      <PageNumber>12215</PageNumber>
    </MainItem>
    <SubItem>
      <Text>(trd.)</Text>
      <PageNumber>9962</PageNumber>
    </SubItem>
  </ItemGroup>
  <ItemGroup>
    <MainItem>
      <Key>
        <KeyDitto>—</KeyDitto>
      </Key>
      <Title>(temp.) 2nd Lt.</Title>
      <Forenames>S. A. H.</Forenames>
      <PageNumber>11157</PageNumber>
    </MainItem>
  </ItemGroup>
  <ItemGroup>
    <MainItem>
      <Key>
        <KeyDitto>—</KeyDitto>
      </Key>
      <Title>(temp.) 2nd Lt.</Title>
      <Forenames>S.</Forenames>
      <PageNumber>10607</PageNumber>
    </MainItem>
    <SubItem>
      <Text>10234, (temp.) Lt. T. R. (trd. and temp. Capt.)'</Text>
      <PageNumber>9723</PageNumber>
    </SubItem>
  </ItemGroup>
  <ItemGroup>
    <MainItem>
      <Key>Groome</Key>
      <Title>(temp.) Lt.</Title>
      <Forenames>C</Forenames>
      <Text>P. (temp</Text>
      <PageNumber>10723</PageNumber>
    </MainItem>
  </ItemGroup>
  <ItemGroup>
    <MainItem>
      <Key>Groove</Key>
      <Title>(temp.) Capt.</Title>
      <Text>f-rd.)</Text>
      <PageNumber>10826</PageNumber>
    </MainItem>
  </ItemGroup>
  <ItemGroup>
    <MainItem>
      <Key>Gros</Key>
      <Title>Cadet</Title>
      <Forenames>C. H.</Forenames>
      <Text>(temp. Lt. on prob.) ,</Text>
      <PageNumber>9749</PageNumber>
    </MainItem>
  </ItemGroup>
  <ItemGroup>
    <MainItem>
      <Key>Groscock</Key>
      <Title>Pte.</Title>
      <Forenames>G. H.</Forenames>
      <Text>(temp. 2nd Lt. on prob.)</Text>
      <PageNumber>12488</PageNumber>
    </MainItem>
  </ItemGroup>
  <ItemGroup>
    <MainItem>
      <Key>Grose</Key>
      <Title>(temp.) Lt.</Title>
      <Forenames>E. M.</Forenames>
      <Text>(trd.)</Text>
      <PageNumber>11391</PageNumber>
    </MainItem>
  </ItemGroup>
  <ItemGroup>
    <MainItem>
      <Key>Gross</Key>
      <Title>Serjt.</Title>
      <Forenames>H. G.</Forenames>
      <Text>(2nd Lt.)</Text>
      <PageNumber>10513</PageNumber>
    </MainItem>
    <SubItem>
      <Text>(temp.) 2nd Lt. H. R. (trd. and temp. Lt.)</Text>
      <PageNumber>11974</PageNumber>
    </SubItem>
  </ItemGroup>
  <ItemGroup>
    <MainItem>
      <Key>Grosset</Key>
      <Title>2nd Lt. (temp. Lt.)</Title>
      <Forenames>W . E.</Forenames>
      <Text>' (Flying Offr.)</Text>
      <PageNumber>9636</PageNumber>
    </MainItem>
  </ItemGroup>
  <ItemGroup>
    <MainItem>
      <Key>Grossmith</Key>
      <Title>Batt. Serjt.-Maj.</Title>
      <Text>w! (2nd Lt.)</Text>
      <PageNumber>10285</PageNumber>
    </MainItem>
  </ItemGroup>
  <ItemGroup>
    <MainItem>
      <Key>Grosvenor</Key>
      <Title>(temp.) 2nd Lt.</Title>
      <Forenames>G . R.</Forenames>
      <Text>' (trd.)</Text>
      <PageNumber>10504</PageNumber>
    </MainItem>
  </ItemGroup>
  <ItemGroup>
    <MainItem>
      <Key>
        <KeyDitto>—</KeyDitto>
      </Key>
      <Title>2nd Lt.</Title>
      <Forenames>R. A.</Forenames>
      <Text>(Flying Offr.)</Text>
      <PageNumber>11679</PageNumber>
    </MainItem>
  </ItemGroup>
  <ItemGroup>
    <MainItem>
      <Key>
        <KeyDitto>——</KeyDitto>
      </Key>
      <Title>(temp.) Capt.</Title>
      <Forenames>R. B.</Forenames>
      <Text>(resigns commn.)</Text>
      <PageNumber>10976</PageNumber>
    </MainItem>
    <SubItem>
      <Text>(temp.) 2nd Lt. T. (trd.j</Text>
      <PageNumber>10385</PageNumber>
      <PageNumber>10946</PageNumber>
    </SubItem>
  </ItemGroup>
  <ItemGroup>
    <MainItem>
      <Key>Grote</Key>
      <Title>Lt.</Title>
      <Forenames>A. L.</Forenames>
      <Text>(trd., temp. Lt.)</Text>
      <PageNumber>9638</PageNumber>
    </MainItem>
  </ItemGroup>
  <ItemGroup>
    <MainItem>
      <Key>Grove</Key>
      <Title>Cadet</Title>
      <Forenames>A.</Forenames>
      <Text>(temp. 2nd Lt. on prob.)</Text>
      <PageNumber>12066</PageNumber>
    </MainItem>
    <SubItem>
      <Text>(temp.) 2nd Lt. A. T. M. (cashiered by sentence of G. C. M.) ..:</Text>
      <PageNumber>11569</PageNumber>
    </SubItem>
    <SubItem>
      <Text>E. G. (temp. Lt.)</Text>
      <PageNumber>10731</PageNumber>
    </SubItem>
    <SubItem>
      <Text>
        <PageNumber>9638</PageNumber>
      </Text>
      <SubCategoryTitle>(Sub. Not.) ..</SubCategoryTitle>
      <PageNumber>9639</PageNumber>
    </SubItem>
  </ItemGroup>
  <ItemGroup>
    <MainItem>
      <Key>
        <KeyDitto />
      </Key>
      <Title>Cadet</Title>
      <Forenames>R. E.</Forenames>
      <Text>(temp. 2nd Lt. on prob.)</Text>
      <PageNumber>11257</PageNumber>
    </MainItem>
    <SubItem>
      <Text>' Batt. Serjt.-Maj. W. H. (2nd Lt.)</Text>
      <PageNumber>11125</PageNumber>
    </SubItem>
  </ItemGroup>
  <ItemGroup>
    <MainItem>
      <Key>Grove-Price</Key>
      <Title>Cadet</Title>
      <Forenames>W. F.</Forenames>
      <Text>(temp. 2nd Lt. on prob.)</Text>
      <PageNumber>10085</PageNumber>
    </MainItem>
  </ItemGroup>
  <ItemGroup>
    <MainItem>
      <Key>Grover</Key>
      <Title>2nd Lt. (temp. Lt.)</Title>
      <Forenames>E</Forenames>
      <Text>C. (actg. Capt.)</Text>
      <PageNumber>10286</PageNumber>
    </MainItem>
    <SubItem>
      <Text>
        <PageNumber>10749</PageNumber>
        <PageNumber>11568</PageNumber>
      </Text>
      <PageNumber>9535</PageNumber>
    </SubItem>
  </ItemGroup>
  <ItemGroup>
    <MainItem>
      <Key>
        <KeyDitto>—</KeyDitto>
      </Key>
      <Title>(temp.) Capt.</Title>
      <Forenames>P. G.</Forenames>
      <Text>(trd.)</Text>
      <PageNumber>11393</PageNumber>
    </MainItem>
  </ItemGroup>
  <ItemGroup>
    <MainItem>
      <Key>Groves</Key>
      <Forenames>A. J.</Forenames>
      <Text>(temp. Hon. Lt.)</Text>
      <PageNumber>10825</PageNumber>
    </MainItem>
    <SubItem>
      <Text>(temp.) 2nd Lt. B. T. (temp. Lt.)</Text>
      <PageNumber>9637</PageNumber>
    </SubItem>
  </ItemGroup>
  <ItemGroup>
    <MainItem>
      <Key>
        <KeyDitto>-—</KeyDitto>
      </Key>
      <Title>Lt.</Title>
      <Forenames>E.</Forenames>
      <Text>J. (actg. Capt.) '</Text>
      <PageNumber>10939</PageNumber>
    </MainItem>
  </ItemGroup>
</Index>

